{
  "employees": [
    [
      "chantell",
      "hlungwani",
      "ntivochantell@gmail.com",
      "C:\\fakepath\\myWork.jpg",
      "2003-01-08",
      "I love Jesus too",
      "smart invester",
      "54554"
    ],
    {
      "name": "John Doe",
      "position": "Manager",
      "id": 1686138799570
    },
    {
      "id": 1686139755097,
      "name": "fadf",
      "surname": "sdfsd",
      "email": "zva",
      "image": "blob:http://localhost:3000/d443d6d1-ba6a-4cc5-8d05-376928e2158d",
      "dateOfBirth": "",
      "biography": "XZczxv",
      "position": "zxczx",
      "cellPhone": "1421"
    },
    {
      "id": 1686141778431,
      "name": "VZXCV",
      "surname": "XZVXC",
      "email": "V XV",
      "image": "blob:http://localhost:3000/a4c6407f-df6d-40ca-b2c0-bde351ebccad",
      "dateOfBirth": "",
      "biography": "FDSFSAF",
      "position": "DSFASDF",
      "cellPhone": "12424"
    },
    {
      "id": 1686141809545,
      "name": "ReS",
      "surname": "XFSAFS",
      "email": "FSDFDS",
      "image": "blob:http://localhost:3000/a4c6407f-df6d-40ca-b2c0-bde351ebccad",
      "dateOfBirth": "",
      "biography": "FDSFSAF",
      "position": "DSFASDF",
      "cellPhone": "12424"
    },
    {
      "id": 1686144841205,
      "name": "ReS",
      "surname": "XFSAFS",
      "email": "FSDFDS",
      "image": "C:\\fakepath\\adidas-porsche-design-sport-ss17-collection-26-removebg-preview.png",
      "dateOfBirth": "",
      "biography": "FDSFSAF",
      "position": "DSFASDF",
      "cellPhone": "12424"
    },
    {
      "id": 1686144842035,
      "name": "ReS",
      "surname": "XFSAFS",
      "email": "FSDFDS",
      "image": "C:\\fakepath\\adidas-porsche-design-sport-ss17-collection-26-removebg-preview.png",
      "dateOfBirth": "",
      "biography": "FDSFSAF",
      "position": "DSFASDF",
      "cellPhone": "12424"
    },
    {
      "id": 1686145115181,
      "name": "ReS",
      "surname": "XFSAFS",
      "email": "FSDFDS",
      "image": "C:\\fakepath\\adidas-porsche-design-sport-ss17-collection-26-removebg-preview.png",
      "dateOfBirth": "",
      "biography": "FDSFSAF",
      "position": "DSFASDF",
      "cellPhone": "12424"
    },
    {
      "id": 1686145157420,
      "name": "",
      "surname": "",
      "email": "",
      "image": "C:\\fakepath\\adidas-porsche-design-sport-ss17-collection-28-removebg-preview.png",
      "dateOfBirth": "",
      "biography": "",
      "position": "",
      "cellPhone": ""
    },
    {
      "id": 1686145294124,
      "name": "",
      "surname": "",
      "email": "",
      "image": "adidas-porsche-design-sport-ss17-collection-28.jpg",
      "dateOfBirth": "",
      "biography": "",
      "position": "",
      "cellPhone": ""
    }
  ]
}